cbor_diag-1.1.2.dist-info/METADATA
cbor_diag-1.1.2.dist-info/WHEEL
cbor_diag/__init__.py
cbor_diag/_cbor_diag.cpython-311-i386-linux-gnu.so
cbor_diag-1.1.2.dist-info/RECORD
