Metadata-Version: 2.4
Name: cbor-diag
Version: 1.1.2
Classifier: Development Status :: 6 - Mature
Classifier: Intended Audience :: Developers
Classifier: Programming Language :: Python :: Implementation :: CPython
Classifier: Programming Language :: Python :: Implementation :: PyPy
Classifier: Programming Language :: Rust
Summary: Conversion between CBOR and CBOR Diagnostic Notation
License: MIT OR Apache-2.0
Project-URL: Documentation, https://cbor-diag.readthedocs.io
Project-URL: Source Code, https://github.com/chrysn/cbor-diag-py
